residuated_binars/__init__.py
residuated_binars/abelian_group.py
residuated_binars/add_task.py
residuated_binars/algebraic_structure.py
residuated_binars/axiom_checkers.py
residuated_binars/boolean_ring.py
residuated_binars/bounded_lattice.py
residuated_binars/check_assumptions.py
residuated_binars/constants.py
residuated_binars/filter_theories.py
residuated_binars/generate_theories.py
residuated_binars/lattice.py
residuated_binars/parser.py
residuated_binars/pseudo_r0_algebra.py
residuated_binars/pseudo_weak_r0_algebra.py
residuated_binars/py.typed
residuated_binars/residuated_binar.py
residuated_binars/resources/isabelle.out
residuated_binars/resources/isabelle2.out
residuated_binars/use_nitpick.py
residuated_binars/utils.py
residuated_binars-0.0.4.dist-info/LICENSE
residuated_binars-0.0.4.dist-info/WHEEL
residuated_binars-0.0.4.dist-info/METADATA
residuated_binars-0.0.4.dist-info/RECORD
