Metadata-Version: 2.1
Name: residuated-binars
Version: 0.0.4
Summary: Package for generating and validating examples of different algebraic structures using Isabelle proof assistant
Home-page: https://github.com/inpefess/residuated-binars
License: Apache-2.0
Author: Boris Shminke
Author-email: boris@shminke.ml
Requires-Python: >=3.7.1,<3.11
Classifier: Development Status :: 7 - Inactive
Classifier: Environment :: Console
Classifier: Intended Audience :: Science/Research
Classifier: License :: OSI Approved :: Apache Software License
Classifier: Natural Language :: English
Classifier: Operating System :: OS Independent
Classifier: Programming Language :: Python :: 3
Classifier: Programming Language :: Python :: 3.10
Classifier: Programming Language :: Python :: 3.7
Classifier: Programming Language :: Python :: 3.8
Classifier: Programming Language :: Python :: 3.9
Classifier: Topic :: Scientific/Engineering :: Artificial Intelligence
Classifier: Typing :: Typed
Requires-Dist: graphviz
Requires-Dist: importlib_resources; python_version < "3.9"
Requires-Dist: isabelle-client
Requires-Dist: nest-asyncio
Requires-Dist: pydocstyle
Project-URL: Repository, https://github.com/inpefess/residuated-binars
